auto4dstem/__init__.py
auto4dstem/Data/DataProcess.py
auto4dstem/Data/__init__.py
auto4dstem/Viz/__init__.py
auto4dstem/Viz/util.py
auto4dstem/Viz/viz.py
auto4dstem/nn/CC_ST_AE.py
auto4dstem/nn/Loss_Function.py
auto4dstem/nn/Train_Function.py
auto4dstem/nn/__init__.py
Auto4DSTEM-0.2.8.dist-info/LICENSE.txt
Auto4DSTEM-0.2.8.dist-info/METADATA
Auto4DSTEM-0.2.8.dist-info/WHEEL
Auto4DSTEM-0.2.8.dist-info/entry_points.txt
Auto4DSTEM-0.2.8.dist-info/top_level.txt
Auto4DSTEM-0.2.8.dist-info/RECORD
