Metadata-Version: 2.2
Name: Auto4DSTEM
Version: 0.2.8
Summary: Incorporating Developed Cycle-Consistent-Spatial-Transforming Autoencoder for 4-D STEM analysis.
Home-page: https://github.com/m3-learning/Auto4DSTEM/
Author: Shuyu Qin, Joshua Agar
Author-email: shq219@lehigh.edu, jca92@drexel.edu
License: MIT
Platform: any
Classifier: Development Status :: 4 - Beta
Classifier: Programming Language :: Python
Requires-Python: >=3.10.6
License-File: LICENSE.txt
Requires-Dist: importlib-metadata
Requires-Dist: cmcrameri==1.8
Requires-Dist: cupy-cuda12x==13.0.0
Requires-Dist: h5py
Requires-Dist: matplotlib==3.6.2
Requires-Dist: numba==0.58.1
Requires-Dist: numpy==1.25.2
Requires-Dist: opencv-python-headless==4.11.0.86
Requires-Dist: py4DSTEM==0.14.9
Requires-Dist: pymatgen==2024.3.1
Requires-Dist: scikit-image==0.19.3
Requires-Dist: scikit-learn==1.1.3
Requires-Dist: scipy==1.9.3
Requires-Dist: torch==2.2.0
Requires-Dist: tqdm==4.66.1
Requires-Dist: typing_extensions==4.8.0
Provides-Extra: testing
Requires-Dist: setuptools; extra == "testing"
Requires-Dist: pytest; extra == "testing"
Requires-Dist: pytest-cov; extra == "testing"
